MANIFEST.in
README.rst
TITLE.txt
lh-agpl3-LICENSE.txt
setup.py
bin/bx822-qmail-remote.py
bin/dsnMsgPlugin.py
bin/fbxoMarmeSetup.sh
bin/inMailDsnPlugin.py
bin/inMailDsnProc.py
bin/inMailNotmuch.py
bin/inMailRetrieve.py
bin/marmeAcctsManage.py
bin/marmeMsgLib.py
bin/marmeRuns.py
bin/marmeSendExample.py
bin/marmeSendIcm.py
bin/marmeTrackingIcm.py
bin/pkgMarmeManage.py
unisos/__init__.py
unisos.marme.egg-info/PKG-INFO
unisos.marme.egg-info/SOURCES.txt
unisos.marme.egg-info/dependency_links.txt
unisos.marme.egg-info/namespace_packages.txt
unisos.marme.egg-info/not-zip-safe
unisos.marme.egg-info/requires.txt
unisos.marme.egg-info/top_level.txt
unisos/marme/__init__.py
unisos/marme/marmeAcctsLib.py
unisos/marme/marmePkgThis.py
unisos/marme/marmeSendLib.py
unisos/marme/marmeTrackingLib.py
unisos/marme-base/template.readOnly
unisos/marme-base/admin/Panel.org
unisos/marme-base/admin/bx822-qmail.org
unisos/marme-base/admin/dsnProc.org
unisos/marme-base/admin/foreignSo-deploy.org
unisos/marme-base/admin/inComingMail.org
unisos/marme-base/admin/installConfig.org
unisos/marme-base/admin/outGoingMail.org
unisos/marme-base/admin/runCmnds.org
unisos/marme-base/admin/siteMarmeManage.py
unisos/marme-base/admin/siteMarmeManage.py.2to3
unisos/marme-base/admin/siteMarmeManage.py.3
unisos/marme-base/inputs/notmuch/_notmuch-config.template
unisos/marme-config/pkgInfo/fp/icmsPkgBasesPolicy/_tree_
unisos/marme-config/pkgInfo/fp/icmsPkgBasesPolicy/value
unisos/marme-config/pkgInfo/fp/icmsPkgControlBaseDir/_tree_
unisos/marme-config/pkgInfo/fp/icmsPkgControlBaseDir/value
unisos/marme-config/pkgInfo/fp/icmsPkgControlName/_tree_
unisos/marme-config/pkgInfo/fp/icmsPkgControlName/value
unisos/marme-config/pkgInfo/fp/icmsPkgLogBaseDir/_tree_
unisos/marme-config/pkgInfo/fp/icmsPkgLogBaseDir/value
unisos/marme-config/pkgInfo/fp/icmsPkgName/_tree_
unisos/marme-config/pkgInfo/fp/icmsPkgName/value
unisos/marme-config/pkgInfo/fp/icmsPkgTmpBaseDir/_tree_
unisos/marme-config/pkgInfo/fp/icmsPkgTmpBaseDir/value
unisos/marme-config/pkgInfo/fp/icmsPkgVarBaseDir/_tree_
unisos/marme-config/pkgInfo/fp/icmsPkgVarBaseDir/value
unisos/marme-fbxo/exMarme/fbxoMarmeSetup.sh
unisos/marme-fbxo/exMarme/so/r3/sr/marme/dsnProc/adapt/admin/fbxoMarmeSetup.sh
